sra_downloader/__init__.py
sra_downloader/__main__.py
sra_downloader/download.py
sra_downloader-1.0.7.dist-info/LICENSE
sra_downloader-1.0.7.dist-info/METADATA
sra_downloader-1.0.7.dist-info/WHEEL
sra_downloader-1.0.7.dist-info/entry_points.txt
sra_downloader-1.0.7.dist-info/top_level.txt
sra_downloader-1.0.7.dist-info/RECORD
