Metadata-Version: 2.1
Name: sra-downloader
Version: 1.0.7
Summary: A script for batch-downloading and automatic compression of data from NCBI Sequence Read Archive. Built on SRA-Toolkit.
Home-page: https://github.com/bioinf-mcb/sra-downloader
Author: Valentyn Bezshapkin & Witold Wydmański
Author-email: witold.wydmanski@uj.edu.pl
License: MIT
Platform: UNKNOWN
